[
    {
        "default": {
            "svm": 0.0,
            "knn": -42.10639042233811,
            "random_forest": -2.4148087031970245,
            "decision_tree": -49.787070686723844
        },
        "random": {
            "svm": 84.83202555730712,
            "knn": 47.210651233829296,
            "random_forest": 64.94792110753154,
            "decision_tree": 45.264477592269486
        }
    },
    {
        "default": {
            "svm": 0.0,
            "knn": -32.590573550582555,
            "random_forest": 2.28716572808068,
            "decision_tree": -70.17608591155428
        },
        "random": {
            "svm": 70.02548812229185,
            "knn": 68.45488289421982,
            "random_forest": 72.36756298171643,
            "decision_tree": 33.93225130172283
        }
    },
    {
        "default": {
            "svm": 0.0,
            "knn": -30.730886501066745,
            "random_forest": -0.8186456829362153,
            "decision_tree": -74.4577099109324
        },
        "random": {
            "svm": 63.36516820392968,
            "knn": 63.245215460851114,
            "random_forest": 58.19560755223516,
            "decision_tree": 43.12239928963187
        }
    },
    {
        "default": {
            "svm": 0.0,
            "knn": -39.71531055220315,
            "random_forest": -2.2539703299874714,
            "decision_tree": -52.86767835818432
        },
        "random": {
            "svm": 69.01546374040981,
            "knn": 49.35556058168911,
            "random_forest": 67.61684748408742,
            "decision_tree": 53.137015971555925
        }
    },
    {
        "default": {
            "svm": 0.0,
            "knn": -36.362672846744786,
            "random_forest": -0.7061333283278579,
            "decision_tree": -85.92185259901296
        },
        "random": {
            "svm": 78.31453030043943,
            "knn": 57.68220109251455,
            "random_forest": 63.97953186815112,
            "decision_tree": 53.81555478364961
        }
    },
    {
        "default": {
            "svm": 0.0,
            "knn": -28.105496537499334,
            "random_forest": -3.5160615099045294,
            "decision_tree": -51.70193394970425
        },
        "random": {
            "svm": 66.84476390051111,
            "knn": 52.06842192894419,
            "random_forest": 59.15049646794473,
            "decision_tree": 46.70388055191663
        }
    },
    {
        "default": {
            "svm": 0.0,
            "knn": -35.821553816313745,
            "random_forest": -0.6369375511561751,
            "decision_tree": -66.01231142054097
        },
        "random": {
            "svm": 75.17415747111377,
            "knn": 52.51002183131524,
            "random_forest": 73.67881542751947,
            "decision_tree": 57.19068331037932
        }
    },
    {
        "default": {
            "svm": 0.0,
            "knn": -46.27138913914516,
            "random_forest": 10.168127888258184,
            "decision_tree": -54.1353193996156
        },
        "random": {
            "svm": 65.59236990498543,
            "knn": 56.52430380723559,
            "random_forest": 55.526892284747774,
            "decision_tree": 59.84442984550194
        }
    },
    {
        "default": {
            "svm": 0.0,
            "knn": -27.819292893172186,
            "random_forest": -0.30339878448364294,
            "decision_tree": -50.6215449342305
        },
        "random": {
            "svm": 55.723664014533426,
            "knn": 54.097308828732004,
            "random_forest": 67.30945972467114,
            "decision_tree": 48.81199660926552
        }
    },
    {
        "default": {
            "svm": 0.0,
            "knn": -42.43114934311106,
            "random_forest": -17.633832682049817,
            "decision_tree": -57.600347182862635
        },
        "random": {
            "svm": 72.75778187498041,
            "knn": 41.202614948244836,
            "random_forest": 54.35108129873034,
            "decision_tree": 53.03410382725967
        }
    },
    {
        "default": {
            "svm": 0.0,
            "knn": -43.50890851845766,
            "random_forest": -7.263148864712424,
            "decision_tree": -46.49279548780687
        },
        "random": {
            "svm": 57.10471765482596,
            "knn": 58.877499082003595,
            "random_forest": 73.03606706437026,
            "decision_tree": 49.04557728762935
        }
    },
    {
        "default": {
            "svm": 0.0,
            "knn": -48.327999062481034,
            "random_forest": -1.5000473749670382,
            "decision_tree": -75.75591081492337
        },
        "random": {
            "svm": 69.27312192689628,
            "knn": 40.211938029407804,
            "random_forest": 63.21926934743418,
            "decision_tree": 37.46221246767431
        }
    },
    {
        "default": {
            "svm": 0.0,
            "knn": -37.37800673907586,
            "random_forest": -2.9175443110228896,
            "decision_tree": -50.36350403488016
        },
        "random": {
            "svm": 72.13794281050033,
            "knn": 50.44668659327923,
            "random_forest": 79.22865010215382,
            "decision_tree": 65.38032270340518
        }
    },
    {
        "default": {
            "svm": 0.0,
            "knn": -26.990487204065538,
            "random_forest": 7.087332560369922,
            "decision_tree": -54.22853745941902
        },
        "random": {
            "svm": 74.7355278372357,
            "knn": 60.737692058146166,
            "random_forest": 87.24451345511014,
            "decision_tree": 48.468319035298315
        }
    },
    {
        "default": {
            "svm": 0.0,
            "knn": -29.042209627608074,
            "random_forest": 3.7626172284980353,
            "decision_tree": -40.90594813596859
        },
        "random": {
            "svm": 74.8512148570038,
            "knn": 61.733820674972264,
            "random_forest": 70.37384470458935,
            "decision_tree": 57.460413536431474
        }
    },
    {
        "default": {
            "svm": 0.0,
            "knn": -29.86114668569615,
            "random_forest": -4.956174568709488,
            "decision_tree": -51.08322813183042
        },
        "random": {
            "svm": 63.36590191352664,
            "knn": 55.1335354998878,
            "random_forest": 65.04452103839427,
            "decision_tree": 57.47147016177136
        }
    },
    {
        "default": {
            "svm": 0.0,
            "knn": -27.96943222710936,
            "random_forest": 6.000390177248895,
            "decision_tree": -60.88206343631335
        },
        "random": {
            "svm": 86.98834756500864,
            "knn": 56.02172613347,
            "random_forest": 71.62279705261335,
            "decision_tree": 52.71942832690157
        }
    },
    {
        "default": {
            "svm": 0.0,
            "knn": -44.73163517571729,
            "random_forest": -3.6065305231926787,
            "decision_tree": -50.08040505987713
        },
        "random": {
            "svm": 60.1007171769887,
            "knn": 50.18643323356638,
            "random_forest": 63.011027241243546,
            "decision_tree": 47.19845282345029
        }
    },
    {
        "default": {
            "svm": 0.0,
            "knn": -33.23513382247868,
            "random_forest": -3.42499395115116,
            "decision_tree": -51.319898636370496
        },
        "random": {
            "svm": 63.70384345131952,
            "knn": 59.931833008996314,
            "random_forest": 62.44516798299728,
            "decision_tree": 42.38313302832438
        }
    },
    {
        "default": {
            "svm": 0.0,
            "knn": -37.97372695841027,
            "random_forest": -6.638693080470155,
            "decision_tree": -59.73488658827696
        },
        "random": {
            "svm": 64.94797578780455,
            "knn": 59.622343737360254,
            "random_forest": 66.64677987577019,
            "decision_tree": 58.12657527702926
        }
    },
    {
        "default": {
            "svm": 0.0,
            "knn": -39.79627365242753,
            "random_forest": 5.198149150007159,
            "decision_tree": -79.53289338583774
        },
        "random": {
            "svm": 63.59515903547056,
            "knn": 53.05373307043138,
            "random_forest": 65.74527388278588,
            "decision_tree": 42.366010274779114
        }
    },
    {
        "default": {
            "svm": 0.0,
            "knn": -30.63633356754559,
            "random_forest": 1.3662996419484006,
            "decision_tree": -59.60303212825717
        },
        "random": {
            "svm": 60.573149735037155,
            "knn": 48.06832865561289,
            "random_forest": 73.06859836576926,
            "decision_tree": 49.25707629981248
        }
    },
    {
        "default": {
            "svm": 0.0,
            "knn": -38.66323339521403,
            "random_forest": 5.368311304421654,
            "decision_tree": -78.52692958052224
        },
        "random": {
            "svm": 59.6822639753988,
            "knn": 59.53851185724861,
            "random_forest": 65.2362697206662,
            "decision_tree": 40.5425304751932
        }
    },
    {
        "default": {
            "svm": 0.0,
            "knn": -44.06760702931822,
            "random_forest": -4.775267598635036,
            "decision_tree": -66.30761457338973
        },
        "random": {
            "svm": 80.48188075630438,
            "knn": 50.084995495956576,
            "random_forest": 66.81811351241642,
            "decision_tree": 56.83811521304184
        }
    },
    {
        "default": {
            "svm": 0.0,
            "knn": -38.980770314650115,
            "random_forest": 5.45184196861233,
            "decision_tree": -65.30824945484022
        },
        "random": {
            "svm": 80.07447506808539,
            "knn": 62.31729646899055,
            "random_forest": 74.71765983585212,
            "decision_tree": 45.94038537863668
        }
    }
]